image_processing/__init__.py
image_processing/processing/__init__.py
image_processing/processing/combination.py
image_processing/processing/transformation.py
image_processing/utils/__init__.py
image_processing/utils/io.py
image_processing/utils/plot.py
bergcastro_image_processing-0.1.3.dist-info/METADATA
bergcastro_image_processing-0.1.3.dist-info/WHEEL
bergcastro_image_processing-0.1.3.dist-info/top_level.txt
bergcastro_image_processing-0.1.3.dist-info/RECORD
