Metadata-Version: 2.1
Name: bergcastro-image-processing
Version: 0.1.3
Summary: Pacote de processamento de imagens
Home-page: https://github.com/BergCastro/image-processing-package
Author: Lindemberg Castro
Author-email: lindembergncastro@outlook.com
License: UNKNOWN
Platform: UNKNOWN
Classifier: Programming Language :: Python :: 3
Classifier: License :: OSI Approved :: MIT License
Classifier: Operating System :: OS Independent
Requires-Python: >=3.9
Requires-Dist: numpy (==1.23.5)
Requires-Dist: scikit-image (==0.19.3)
